Metadata-Version: 1.0
Name: cargo-phone-number-field
Version: 0.1.0
Summary: A phone number field type for Cargo ORM.
Home-page: https://github.com/jaredlunde/cargo_phone_number
Author: Jared Lunde
Author-email: jared.lunde@gmail.com
License: MIT
Platform: UNKNOWN
